app/__init__.py
app/cli.py
app/main.py
app/auth/__init__.py
app/auth/auth_interface.py
app/auth/auth_jwks.py
app/auth/exceptions.py
app/auth/mcp_auth_provider.py
app/auth/models.py
app/auth/oauth2.py
app/config/__init__.py
app/config/app.py
app/config/auth.py
app/config/logging.py
app/interfaces/__init__.py
app/interfaces/http_client.py
app/middleware/__init__.py
app/middleware/oauth2.py
app/middleware/proxy.py
app/middleware/pygeoapi.py
app/pygeoapi/__init__.py
app/pygeoapi/models.py
app/pygeoapi/openapi.py
app/pygeoapi/starlette_app.py
app/pygeoapi/api/__init__.py
app/pygeoapi/api/processes.py
app/schemas/logging.py
app/utils/__init__.py
app/utils/app_exceptions.py
app/utils/get_list_of_app_exceptions_for_frontend.py
app/utils/openapi_generator.py
app/utils/openapi_resolver.py
app/utils/pygeoapi_exceptions.py
app/utils/pygeoapi_utils.py
app/utils/request_exceptions.py
app/utils/service_result.py
fastgeoapi-0.0.8.dist-info/METADATA
fastgeoapi-0.0.8.dist-info/WHEEL
fastgeoapi-0.0.8.dist-info/entry_points.txt
fastgeoapi-0.0.8.dist-info/licenses/LICENSE.md
fastgeoapi-0.0.8.dist-info/RECORD
