Metadata-Version: 2.4
Name: fastgeoapi
Version: 0.0.8
Summary: fastgeoapi
Project-URL: Homepage, https://github.com/geobeyond/fastgeoapi
Project-URL: Repository, https://github.com/geobeyond/fastgeoapi
Project-URL: Documentation, https://geobeyond.github.io/fastgeoapi/
Project-URL: Changelog, https://github.com/geobeyond/fastgeoapi/releases
Author-email: Francesco Bartoli <francesco.bartoli@geobeyond.it>
Maintainer-email: Youssef Harby <youssef.harby@geobeyond.it>
License-Expression: MIT
License-File: LICENSE.md
Classifier: Development Status :: 4 - Beta
Requires-Python: <3.14,>=3.12
Requires-Dist: authlib<2,>=1.5.2
Requires-Dist: cachetools<6,>=5.5.2
Requires-Dist: fastapi-key-auth<0.16.0,>=0.15.4
Requires-Dist: fastapi-opa<3,>=2.0.3
Requires-Dist: fastapi[standard]<1.0,>=0.126
Requires-Dist: fastmcp>=2.14.1
Requires-Dist: fencer
Requires-Dist: geoalchemy2<0.18,>=0.17.1
Requires-Dist: json-ref-dict<=1.0,>=0.7.2
Requires-Dist: loguru<1.0,>=0.7.3
Requires-Dist: mangum<1.0,>=0.19
Requires-Dist: mcpauth==0.2.0b1
Requires-Dist: openapi-pydantic<=1.0,>=0.5.1
Requires-Dist: psycopg2-binary<3,>=2.9.10
Requires-Dist: pydantic-settings<3,>=2.9.1
Requires-Dist: pygeoapi>=0.22.0
Requires-Dist: pygeofilter
Requires-Dist: pyyaml<7,>=6.0.2
Requires-Dist: rasterio<2,>=1.4.3
Requires-Dist: scalar-fastapi<2,>=1.4.3
Requires-Dist: shapely<3,>=2.0
Requires-Dist: sqlalchemy<2.1,>=2.0.40
Requires-Dist: typer<0.16,>=0.15.3
